fastapi_generator/__init__.py
fastapi_generator/api.py
fastapi_generator/command.py
fastapi_generator/config.py
fastapi_generator/data.py
fastapi_generator/main.py
fastapi_generator/sub.py
fastapi_generator/templates/.gitignore
fastapi_generator/templates/README.md
fastapi_generator/templates/__init__.py
fastapi_generator/templates/requirements.txt
fastapi_generator/templates/api/api
fastapi_generator/templates/app/__init__.py
fastapi_generator/templates/app/config.py
fastapi_generator/templates/app/data.py
fastapi_generator/templates/app/db.py
fastapi_generator/templates/app/interface.py
fastapi_generator/templates/app/main.py
fastapi_generator/templates/app/models.py
fastapi_generator/templates/app/utils.py
fastapi_generator/templates/sub/app
fastapi_generator/templates/sub/config
fastapi_generator/templates/sub/help
fastapi_generator/templates/sub/interface
fastapi_generator/utils/__init__.py
fastapi_generator/utils/helper.py
fastapi_generator-0.5.1.dist-info/METADATA
fastapi_generator-0.5.1.dist-info/WHEEL
fastapi_generator-0.5.1.dist-info/entry_points.txt
fastapi_generator-0.5.1.dist-info/top_level.txt
fastapi_generator-0.5.1.dist-info/RECORD
