Metadata-Version: 2.1
Name: fastapi-generator
Version: 0.5.1
Summary: Used to quickly generate fastapi project.
Home-page: https://github.com/StevenLianaL/fastapi_generator
Author: Steven Wang
Author-email: wangzhou8284@outlook.com
License: UNKNOWN
Platform: UNKNOWN
Classifier: Programming Language :: Python :: 3
Classifier: License :: OSI Approved :: MIT License
Requires-Python: >=3.8
Requires-Dist: click
Requires-Dist: fastapi
Requires-Dist: uvicorn
Requires-Dist: sqlalchemy
Requires-Dist: databases
Requires-Dist: aiomysql
Requires-Dist: mysqlclient
Requires-Dist: pandas
